air_hockey/__init__.py
air_hockey/localize_microrobot.py
air_hockey/microrobot_commander.py
air_hockey/neopixel_controller.py
air_hockey/setup.py
air_hockey-0.1.3.dist-info/LICENSE
air_hockey-0.1.3.dist-info/METADATA
air_hockey-0.1.3.dist-info/WHEEL
air_hockey-0.1.3.dist-info/top_level.txt
air_hockey-0.1.3.dist-info/RECORD
