Metadata-Version: 2.1
Name: air_hockey
Version: 0.1.3
Summary: Python package for ROS integrated air-hockey table designed at METU ROMER
Author-email: Tan Çağatay Acar <tancagatayacar@gmail.com>
Project-URL: Homepage, https://github.com/Shauanaa/ME462
Project-URL: Issues, https://github.com/Shauanaa/ME462/issues
Classifier: Programming Language :: Python :: 3
Classifier: License :: OSI Approved :: MIT License
Classifier: Operating System :: OS Independent
Requires-Python: >=3.8
License-File: LICENSE
